crifx/__init__.py
crifx/cli.py
crifx/config_parser.py
crifx/dir_layout_parsing.py
crifx/git_manager.py
crifx/problemset_parser.py
crifx/report_writer.py
crifx/version.py
crifx/contest_objects/__init__.py
crifx/contest_objects/judge.py
crifx/contest_objects/judgement.py
crifx/contest_objects/problem.py
crifx/contest_objects/problem_test_case.py
crifx/contest_objects/problemset.py
crifx/contest_objects/programming_language.py
crifx/contest_objects/submission.py
crifx/report_objects/__init__.py
crifx/report_objects/review_status.py
crifx-0.1.5.dist-info/licenses/LICENSE
crifx-0.1.5.dist-info/METADATA
crifx-0.1.5.dist-info/WHEEL
crifx-0.1.5.dist-info/entry_points.txt
crifx-0.1.5.dist-info/top_level.txt
crifx-0.1.5.dist-info/RECORD
